templated_dictionary/__init__.py
templated_dictionary-1.2.dist-info/LICENSE
templated_dictionary-1.2.dist-info/METADATA
templated_dictionary-1.2.dist-info/WHEEL
templated_dictionary-1.2.dist-info/top_level.txt
templated_dictionary-1.2.dist-info/RECORD
