Metadata-Version: 2.1
Name: templated-dictionary
Version: 1.2
Summary: Dictionary with Jinja2 expansion
Home-page: https://github.com/xsuchy/templated-dictionary
Author: Miroslav Suchý
Author-email: msuchy@redhat.com
License: GPL-2.0-or-later
Classifier: Programming Language :: Python :: 3
Classifier: License :: OSI Approved :: GNU General Public License v2 or later (GPLv2+)
Classifier: Operating System :: OS Independent
License-File: LICENSE
Requires-Dist: jinja2
